toppics/__init__.py
toppics/cli.py
toppics/constants.py
toppics/utils.py
toppics-0.1.1.dist-info/entry_points.txt
toppics-0.1.1.dist-info/LICENSE
toppics-0.1.1.dist-info/WHEEL
toppics-0.1.1.dist-info/METADATA
toppics-0.1.1.dist-info/RECORD
