Metadata-Version: 2.1
Name: toppics
Version: 0.1.1
Summary: A Python CLI for adding pre-defined topics to a GitHub repository.
Home-page: https://github.com/joaopalmeiro/toppics
License: MIT
Keywords: toppics,cli,topics,github,api
Author: João Palmeiro
Author-email: joaommpalmeiro@gmail.com
Requires-Python: >=3.6,<4.0
Classifier: Development Status :: 3 - Alpha
Classifier: Environment :: Console
Classifier: Intended Audience :: Developers
Classifier: Intended Audience :: Information Technology
Classifier: Intended Audience :: Science/Research
Classifier: License :: OSI Approved :: MIT License
Classifier: Natural Language :: English
Classifier: Operating System :: OS Independent
Classifier: Programming Language :: Python :: 3
Classifier: Programming Language :: Python :: 3.6
Classifier: Programming Language :: Python :: 3.7
Classifier: Programming Language :: Python :: 3.8
Classifier: Programming Language :: Python :: 3.9
Classifier: Programming Language :: Python :: Implementation :: CPython
Classifier: Topic :: Software Development :: Version Control :: Git
Classifier: Topic :: Terminals
Classifier: Topic :: Utilities
Requires-Dist: click (>=7.1.2,<8.0.0)
Requires-Dist: ghapi (>=0.1.16,<0.2.0)
Requires-Dist: importlib-metadata (>=1.0,<2.0); python_version < "3.8"
Project-URL: Bug Tracker, https://github.com/joaopalmeiro/toppics/issues
Project-URL: Repository, https://github.com/joaopalmeiro/toppics
Project-URL: Twitter, https://twitter.com/joaompalmeiro
